Workbook

Sheet Income Statement
A34: % Margin | B34: =DCF!B20/DCF!B8 -> 0.22210906 | C34: =DCF!C20/DCF!C8 -> 0.21252272 | D34: =DCF!D20/DCF!D8 -> 0.22182986 | E34: =DCF!E20/DCF!E8 -> 0.2290789 | F34: =DCF!F20/DCF!F8 -> 0.21606992 | G34: =DCF!G20/DCF!G8 -> 0.22679971
A36: Interest Expense | B36: -146.9 | C36: -152.1 | D36: -153.5 | E36: -129.8 | F36: -140.1 | G36: -161.5
A37: % Growth | C37: =(C36-B36)/B36 -> 0.03539823 | D37: =(D36-C36)/C36 -> 0.0092044707 | E37: =(E36-D36)/D36 -> -0.15439739 | F37: =(F36-E36)/E36 -> 0.079352851 | G37: =(G36-F36)/F36 -> 0.15274804
A38: Other Income | B38: 8.021 | C38: 7.997 | D38: 4.097 | E38: 2.429 | F38: 2.538 | G38: 9.726
A39: Total Other Expenses | B39: -138.8 | C39: -144.1 | D39: -149.4 | E39: -127.4 | F39: -137.6 | G39: -151.8
A41: Currency Exchange Gains (Loss) | B41: - | C41: - | D41: - | E41: - | F41: 0.362 | G41: 0
A42: Other Non-Operating Inc. (Exp.) | B42: -3.8 | C42: -0.2 | D42: -0.2 | E42: -0.1 | F42: -4.3 | G42: 5.395
A43: EBT Excl. Unusual Items | B43: 1587.865 | C43: 1552.964 | D43: 1658.289 | E43: 1927.579 | F43: 2109.774 | G43: 2385.788
A45: Restructuring Charges | B45: -51.8 | C45: -9.2 | D45: -31.5 | E45: -16.6 | F45: -4.4 | G45: -3.4
A46: Merger & Related Restruct. Charges | B46: -20.6 | C46: - | D46: - | E46: - | F46: - | G46: -
A47: Impairment of Goodwill | B47: - | C47: - | D47: - | E47: - | F47: - | G47: -
A48: Gain (Loss) On Sale Of Invest. | B48: -50.3 | C48: -50.5 | D48: -131.8 | E48: -113.8 | F48: -188.3 | G48: -210.5
A49: Gain (Loss) On Sale Of Assets | B49: 2.658 | C49: - | D49: - | E49: - | F49: - | G49: -
A50: Asset Writedown | B50: -57.7 | C50: -112.5 | D50: - | E50: - | F50: - | G50: -
A51: Other Unusual Items | B51: - | C51: - | D51: - | E51: - | F51: - | G51: -
A52: EBT Incl. Unusual Items | B52: 1410.061 | C52: 1380.784 | D52: 1494.997 | E52: 1797.224 | F52: 1917.071 | G52: 2171.864
A54: Income Tax Expense | B54: 239.01 | C54: 234.032 | D54: 219.584 | E54: 314.405 | F54: 272.254 | G54: 310.077
A55: Earnings from Cont. Ops. | B55: 1171.051 | C55: 1146.752 | D55: 1275.413 | E55: 1482.819 | F55: 1644.817 | G55: 1861.787
A57: Earnings of Discontinued Ops. | B57: - | C57: - | D57: - | E57: - | F57: - | G57: -
A58: Extraord. Item & Account. Change | B58: - | C58: - | D58: - | E58: - | F58: - | G58: -
A59: Net Income to Company | B59: 1171.051 | C59: 1146.752 | D59: 1275.413 | E59: 1482.819 | F59: 1644.817 | G59: 1861.787
A61: Minority Int. in Earnings | B61: 6.511 | C61: 2.94 | D61: 3.295 | E61: -5.3 | F61: - | G61: -
A62: Net Income | B62: 1177.562 | C62: 1149.692 | D62: 1278.708 | E62: 1477.512 | F62: 1644.817 | G62: 1861.787

Sheet DCF
A4: Income Statement
B5: USD in Millions
A6: Currency | B6: 2018 | C6: 2019 | D6: 2020 | E6: 2021 | F6: 2022 | G6: 2023 | H6: 2024E | I6: 2025E | J6: 2026E | K6: 2027E | L6: 2028E
A8: Revenue | B8: 7791.069 | C8: 7986.252 | D8: 8149.719 | E8: 8971.337 | F8: 10419.294 | G8: 11164.992
A9: % Growth | C9: =(C8-B8)/B8 -> 0.025052146 | D9: =(D8-C8)/C8 -> 0.02046855 | E9: =(E8-D8)/D8 -> 0.1008155 | F9: =(F8-E8)/E8 -> 0.16139813 | G9: =(G8-F8)/F8 -> 0.071568957
A10: Cost Of Goods Sold | B10: 4204.421 | C10: 4363.774 | D10: 4446.241 | E10: 4917.519 | F10: 5920.747 | G10: 6166.649
A12: Gross Profit | B12: 3586.648 | C12: 3622.478 | D12: 3703.478 | E12: 4053.818 | F12: 4498.547 | G12: 4998.343
A13: % Margin | B13: =B12/B8 -> 0.46035377 | C13: =C12/C8 -> 0.45358924 | D13: =D12/D8 -> 0.45443015 | E13: =E12/E8 -> 0.45186331 | F13: =F12/F8 -> 0.43175161 | G13: =G12/G8 -> 0.44767994
A14: Operating Expenses | B14: 1817.66 | C14: 1888.072 | D14: 1855.107 | E14: 1958.567 | F14: 2200.308 | G14: 2416.096
A15: Operating Expenses | B15: =B14+B19 -> 1856.181 | C15: =C14+C19 -> 1925.218 | D15: =D14+D19 -> 1895.627 | E15: =E14+E19 -> 1998.674 | F15: =F14+F19 -> 2247.251 | G15: =G14+G19 -> 2466.126
A16: % Margin | B16: =B15/B8 -> 0.23824471 | C16: =C15/C8 -> 0.24106652 | D16: =D15/D8 -> 0.23260029 | E16: =E15/E8 -> 0.22278441 | F16: =F15/F8 -> 0.2156817 | G16: =G15/G8 -> 0.22088023
A17: Provision for Bad Debts | B17: - | C17: - | D17: 2.943 | E17: - | F17: - | G17: -
A18: R & D Exp. | B18: 38.521 | C18: 37.146 | D18: 37.577 | E18: 40.107 | F18: 46.943 | G18: 50.03
A19: Other Operating Expenses | B19: =SUM(B17,B18) -> 38.521 | C19: =SUM(C17,C18) -> 37.146 | D19: =SUM(D17,D18) -> 40.52 | E19: =SUM(E17,E18) -> 40.107 | F19: =SUM(F17,F18) -> 46.943 | G19: =SUM(G17,G18) -> 50.03
A20: EBIT | B20: 1730.467 | C20: 1697.26 | D20: 1807.851 | E20: 2055.144 | F20: 2251.296 | G20: 2532.217
A21: % Margin | B21: =B20/B8 -> 0.22210906 | C21: =C20/C8 -> 0.21252272 | D21: =D20/D8 -> 0.22182986 | E21: =E20/E8 -> 0.2290789 | F21: =F20/F8 -> 0.21606992 | G21: =G20/G8 -> 0.22679971
A22: Tax Expense | B22: =B20*(B23) -> 294.17939 | C22: =C20*(C23) -> 286.83694 | D22: =D20*(D23) -> 265.7541 | E22: =E20*(E23) -> 359.6502 | F22: =F20*(F23) -> 319.68403 | G22: =G20*(G23) -> 362.10703
A23: Tax Rates | B23: 0.17 | C23: 0.169 | D23: 0.147 | E23: 0.175 | F23: 0.142 | G23: 0.143
A24: Tax Adjusted EBIT | B24: =B20-B22 -> 1436.2876 | C24: =C20-C22 -> 1410.4231 | D24: =D20-D22 -> 1542.0969 | E24: =E20-E22 -> 1695.4938 | F24: =F20-F22 -> 1931.612 | G24: =G20-G22 -> 2170.11
A26: Plus: Depreciation & Amortization
A27: Less: Capital Expenditures
A28: Less:

Sheet Sheet1
B1: Compatibility Report for F9745C40.xls
B2: Run on 3/27/2024 22:44
B4: If the workbook is saved in an earlier file format or opened in an earlier version of Microsoft Excel, the listed features will not be available.
B6: Minor loss of fidelity | E6: # of occurrences | F6: Version
B8: Some cells or styles in this workbook contain formatting that is not supported by the selected file format. These formats will be converted to the closest format available. | E8: 1 | F8: Excel 97-2003
