Workbook

Sheet Terms of Use
A2: Terms of Use
A4: This Document is subject to the Adventis Terms of Use (“TOU”) appearing on its web site. The TOU include, but are not limited to, restrictions on use of Documents, a disclaimer of all warranties and conditions of merchantability, and limitations of liability.
A7: Product protected by copyright
A8: © 2013 Adventis CG Training LLC

Sheet Income Statement
A1: Pepsico Financial Model | L1: This document subject to the Terms of Use
A2: Income Statement ($ in Millions) | L2: © 2013 Adventis CG Training LLC
E6: Fiscal Year Ended December 31,
E7: 2016A | F7: 2017A | G7: 2018A | H7: 2019E | I7: 2020E | J7: 2021E | K7: 2022E | L7: 2023E | N7: Instructions:
A8: Income Statement
A10: Revenue | E10: 62799 | F10: 63525 | G10: 64661 | H10: =+G10*(1+H11) -> 65307.61 | I10: =+H10*(1+I11) -> 66287.224 | J10: =+I10*(1+J11) -> 67612.969 | K10: =+J10*(1+K11) -> 68627.163 | L10: =+K10*(1+L11) -> 69313.435 | N10: Previous Year's Revenue x (1 + Growth Rate)
A11: % Growth | F11: =+F10/E10-1 -> 0.011560694 | G11: =+G10/F10-1 -> 0.017882723 | H11: 0.01 | I11: 0.015 | J11: 0.02 | K11: 0.015 | L11: 0.01 | N11: Revenue / Previous Year's Revenue - 1
A13: Operating Expenses | E13: 52995 | F13: 53249 | G13: 54551 | H13: =+H10-H14 -> 54858.392 | I13: =+I10-I14 -> 55681.268 | J13: =+J10-J14 -> 56794.894 | K13: =+K10-K14 -> 57646.817 | L13: =+L10-L14 -> 58223.285 | N13: Revenue - Operating Income
A14: Operating Income | E14: =+E10-E13 -> 9804 | F14: =+F10-F13 -> 10276 | G14: =+G10-G13 -> 10110 | H14: =+H15*H10 -> 10449.218 | I14: =+I15*I10 -> 10605.956 | J14: =+J15*J10 -> 10818.075 | K14: =+K15*K10 -> 10980.346 | L14: =+L15*L10 -> 11090.15 | N14: % Operating Margin x Revenue
A15: % Operating Margin | E15: =+E14/E$10 -> 0.15611714 | F15: =+F14/F$10 -> 0.16176309 | G15: =+G14/G$10 -> 0.15635391 | H15: 0.16 | I15: 0.16 | J15: 0.16 | K15: 0.16 | L15: 0.16
A17: Interest Expense | E17: 1342 | F17: 1151 | G17: 1525 | H17: =Interest!H20 -> 1113.735 | I17: =Interest!I20 -> 1078.735 | J17: =Interest!J20 -> 933.35874 | K17: =Interest!K20 -> 784.68817 | L17: =Interest!L20 -> 741.2115 | N17: Step 10: Link into the Interest Expense Schedule
A18: Interest Income | E18: -110 | F18: -244 | G18: -306 | H18: =-Interest!H32 -> -296.50444 | I18: =-Interest!I32 -> -254.13611 | J18: =-Interest!J32 -> -144.98167 | K18: =-Interest!K32 -> -45 | L18: =-Interest!L32 -> -45 | N18: Step 10: Link into the Interest Income Schedule
A19: Other Expense (Income) | E19: 19 | F19: -233 | G19: -298 | H19: -200 | I19: -225 | J19: -250 | K19: -300 | L19: -350
A20: Total Other Expenses | E20: =SUM(E17:E19) -> 1251 | F20: =SUM(F17:F19) -> 674 | G20: =SUM(G17:G19) -> 921 | H20: =SUM(H17:H19) -> 617.23056 | I20: =SUM(I17:I19) -> 599.59889 | J20: =SUM(J17:J19) -> 538.37706 | K20: =SUM(K17:K19) -> 439.68817 | L20: =SUM(L17:L19) -> 346.2115
A22: Earnings Before Taxes | E22: =+E14-E20 -> 8553 | F22: =+F14-F20 -> 9602 | G22: =+G14-G20 -> 9189 | H22: =+H14-H20 -> 9831.987 | I22: =+I14-I20 -> 10006.357 | J22: =+J14-J20 -> 10279.698 | K22: =+K14-K20 -> 10540.658 | L22: =+L14-L20 -> 10743.938 | N22: Operating Income - Total Other Expenses
A24: Corporate Taxes | E24: 2174 | F24: 4694 | G24: -3370 | H24: =+H22*H29 -> 2556.3166 | I24: =+I22*I29 -> 2601.6528 | J24: =+J22*J29 -> 2672.7215 | K24: =+K22*K29 -> 2740.5711 | L24: =+L22*L29 -> 2793.4239 | N24: Earnings Before Taxes x Corporate Tax Rate
A25: Net Earnings | E25: =+E22-E24 -> 6379 | F25: =+F22-F24 -> 4908 | G25: =+G22-G24 -> 12559 | H25: =+H22-H24 -> 7275.6704 | I25: =+I22-I24 -> 7404.7042 | J25: =+J22-J24 -> 7606.9765 | K25: =+K22-K24 -> 7800.0869 | L25: =+L22-L24 -> 7950.5142 | N25: Earnings Before Taxes - Corporate Taxes
A26: % Net Margin | E26: =+E25/E10 -> 0.10157805 | F26: =+F25/F10 -> 0.077260921 | G26: =+G25/G10 -> 0.19422836 | H26: =+H25/H10 -> 0.11140617 | I26: =+I25/I10 -> 0.11170635 | J26: =+J25/J10 -> 0.11250765 | K26: =+K25/K10 -> 0.11365889 | L26: =+L25/L10 -> 0.1147038 | N26: Net Earnings / Revenue
A28: Metrics & Drivers
A29: Corporate Tax Rate | E29: =+E24/E22 -> 0.25417982 | F29: =+F24/F22 -> 0.48885649 | G29: =+G24/G22 -> -0.36674284 | H29: 0.26 | I29: 0.26 | J29: 0.26 | K29: 0.26 | L29: 0.26 | N29: Corporate Taxes / Earnings before Taxes

Sheet Balance Sheet
A1: =+'Income Statement'!A1 -> Pepsico Financial Model | L1: This document subject to the Terms of Use
A2: Balance Sheet ($ in Millions) | L2: © 2013 Adventis CG Training LLC
E6: Fiscal Year Ended December 31,
E7: 2016A | F7: 2017A | G7: 2018A | H7: 2019E | I7: 2020E | J7: 2021E | K7: 2022E | L7: 2023E | N7: Instructions:
A8: Balance Sheet
A10: Cash and Cash Equivalents | E10: 16125 | F10: =10610+8900 -> 19510 | G10: =8721+272+1997 -> 10990 | H10: ='Cash Flow Statement'!H27 -> 8776.9625 | I10: ='Cash Flow Statement'!I27 -> 8165.4449 | J10: ='Cash Flow Statement'!J27 -> 1500 | K10: ='Cash Flow Statement'!K27 -> 1500 | L10: ='Cash Flow Statement'!L27 -> 1500 | N10: Step 6: Link into the Cash Flow Statement
A11: Accounts Receivable | E11: 6694 | F11: =7024 -> 7024 | G11: 7142 | H11: =+'Working Capital'!H10 -> 7156.9984 | I11: =+'Working Capital'!I10 -> 7244.5054 | J11: =+'Working Capital'!J10 -> 7409.6404 | K11: =+'Working Capital'!K10 -> 7520.785 | L11: =+'Working Capital'!L10 -> 7595.9929 | N11: Step 7: Link into the Working Capital Schedule
A12: Other Current Assets | E12: 3631 | F12: =13393-8900 -> 4493 | G12: =6030-1997-272 -> 3761 | H12: =+'Working Capital'!H11 -> 3918.4566 | I12: =+'Working Capital'!I11 -> 3977.2334 | J12: =+'Working Capital'!J11 -> 4056.7781 | K12: =+'Working Capital'!K11 -> 4117.6298 | L12: =+'Working Capital'!L11 -> 4158.8061 | N12: Step 7: Link into the Working Capital Schedule
A13: Total Current Assets | E13: =SUM(E10:E12) -> 26450 | F13: =SUM(F10:F12) -> 31027 | G13: =SUM(G10:G12) -> 21893 | H13: =SUM(H10:H12) -> 19852.417 | I13: =SUM(I10:I12) -> 19387.184 | J13: =SUM(J10:J12) -> 12966.419 | K13: =SUM(K10:K12) -> 13138.415 | L13: =SUM(L10:L12) -> 13254.799
A15: Net Property, Plant & Equipment | E15: 16591 | F15: 17240 | G15: 17589 | H15: =+'PP&E'!H13 -> 18111.461 | I15: =+'PP&E'!I13 -> 18509.184 | J15: =+'PP&E'!J13 -> 18779.636 | K15: =+'PP&E'!K13 -> 18916.89 | L15: =+'PP&E'!L13 -> 18916.89 | N15: Step 6: Link into the PP&E Schedule
A16: Other Long-Term Assets | E16: 30449 | F16: 31537 | G16: 38166 | H16: 38166 | I16: 38166 | J16: 38166 | K16: 38166 | L16: 38166
A17: Total Assets | E17: =SUM(E15:E16,E13) -> 73490 | F17: =SUM(F15:F16,F13) -> 79804 | G17: =SUM(G15:G16,G13) -> 77648 | H17: =SUM(H15:H16,H13) -> 76129.878 | I17: =SUM(I15:I16,I13) -> 76062.368 | J17: =SUM(J15:J16,J13) -> 69912.055 | K17: =SUM(K15:K16,K13) -> 70221.305 | L17: =SUM(L15:L16,L13) -> 70337.689
A19: Accounts Payable | E19: 13243 | F19: 14017 | G19: 17112 | H19: =+'Working Capital'!H14 -> 16326.903 | I19: =+'Working Capital'!I14 -> 16571.806 | J19: =+'Working Capital'!J14 -> 16903.242 | K19: =+'Working Capital'!K14 -> 17156.791 | L19: =+'Working Capital'!L14 -> 17328.359 | N19: Step 7: Link into the Working Capital Schedule
A20: Other Current Liabilities | E20: 1000 | F20: 1000 | G20: 1000 | H20: =+'Working Capital'!H15 -> 1044.9218 | I20: =+'Working Capital'!I15 -> 1060.5956 | J20: =+'Working Capital'!J15 -> 1081.8075 | K20: =+'Working Capital'!K15 -> 1098.0346 | L20: =+'Working Capital'!L15 -> 1109.015 | N20: Step 7: Link into the Working Capital Schedule
A21: Total Current Liabilities | E21: =SUM(E19:E20) -> 14243 | F21: =SUM(F19:F20) -> 15017 | G21: =SUM(G19:G20) -> 18112 | H21: =SUM(H19:H20) -> 17371.824 | I21: =SUM(I19:I20) -> 17632.402 | J21: =SUM(J19:J20) -> 17985.05 | K21: =SUM(K19:K20) -> 18254.825 | L21: =SUM(L19:L20) -> 18437.374
A23: Total Debt | E23: 36945 | F23: 39281 | G23: 32321 | H23: =+Debt!H37 -> 31321 | I23: =+Debt!I37 -> 30321 | J23: =+Debt!J37 -> 23129.249 | K23: =+Debt!K37 -> 21909.629 | L23: =+Debt!L37 -> 20564.138 | N23: Step 9: Link into the Debt Schedule
A24: Other Long-Term Liabilities | E24: 11103 | F24: 14525 | G24: 12613 | H24: 12613 | I24: 12613 | J24: 12613 | K24: 12613 | L24: 12613
A25: Total Liabilities | E25: =SUM(E23:E24,E21) -> 62291 | F25: =SUM(F23:F24,F21) -> 68823 | G25: =SUM(G23:G24,G21) -> 63046 | H25: =SUM(H23:H24,H21) -> 61305.824 | I25: =SUM(I23:I24,I21) -> 60566.402 | J25: =SUM(J23:J24,J21) -> 53727.299 | K25: =SUM(K23:K24,K21) -> 52777.454 | L25: =SUM(L23:L24,L21) -> 51614.511
A27: Shareholders' Equity | E27: 11199 | F27: 10981 | G27: 14602 | H27: =+Equity!H14 -> 14824.054 | I27: =+Equity!I14 -> 15495.966 | J27: =+Equity!J14 -> 16184.756 | K27: =+Equity!K14 -> 17443.851 | L27: =+Equity!L14 -> 18723.178 | N27: Step 8: Link into the Equity Schedule
A28: Total Liabilities and Equity | E28: =SUM(E27,E25) -> 73490 | F28: =SUM(F27,F25) -> 79804 | G28: =SUM(G27,G25) -> 77648 | H28: =SUM(H27,H25) -> 76129.878 | I28: =SUM(I27,I25) -> 76062.368 | J28: =SUM(J27,J25) -> 69912.055 | K28: =SUM(K27,K25) -> 70221.305 | L28: =SUM(L27,L25) -> 70337.689
A30: check | E30: =+E17-E28 -> 0 | F30: =+F17-F28 -> 0 | G30: =+G17-G28 -> 0 | H30: =+H17-H28 -> 0 | I30: =+I17-I28 -> 0 | J30: =+J17-J28 -> 0 | K30: =+K17-K28 -> 0 | L30: =+L17-L28 -> 0 | N30: Total Assets - Total Liabilities & Equity
A32: Metrics & Drivers
A33: Net Earnings | E33: =+'Income Statement'!E25 -> 6379 | F33: =+'Income Statement'!F25 -> 4908 | G33: =+'Income Statement'!G25 -> 12559 | H33: =+'Income Statement'!H25 -> 7275.6704 | I33: =+'Income Statement'!I25 -> 7404.7042 | J33: =+'Income Statement'!J25 -> 7606.9765 | K33: =+'Income Statement'!K25 -> 7800.0869 | L33: =+'Income Statement'!L25 -> 7950.5142 | N33: Link to the Income Statement
A34: Cash Ratio | E34: =+E10/E21 -> 1.1321351 | F34: =+F10/F21 -> 1.2991942 | G34: =+G10/G21 -> 0.60678004 | H34: =+H10/H21 -> 0.50524127 | I34: =+I10/I21 -> 0.46309318 | J34: =+J10/J21 -> 0.083402605 | K34: =+K10/K21 -> 0.082170055 | L34: =+L10/L21 -> 0.08135649 | N34: Cash and Cash Equivalents / Total Current Liabilities
A35: Return on Equity | E35: =+E33/E27 -> 0.56960443 | F35: =+F33/F27 -> 0.44695383 | G35: =+G33/G27 -> 0.86008766 | H35: =+H33/H27 -> 0.49080166 | I35: =+I33/I27 -> 0.4778472 | J35: =+J33/J27 -> 0.47000873 | K35: =+K33/K27 -> 0.44715395 | L35: =+L33/L27 -> 0.42463487 | N35: Net Earnings / Shareholders' Equity
A36: Net Debt | E36: =+E23-E10 -> 20820 | F36: =+F23-F10 -> 19771 | G36: =+G23-G10 -> 21331 | H36: =+H23-H10 -> 22544.038 | I36: =+I23-I10 -> 22155.555 | J36: =+J23-J10 -> 21629.249 | K36: =+K23-K10 -> 20409.629 | L36: =+L23-L10 -> 19064.138 | N36: Total Debt - Cash and Cash Equivalents
A42: Note: Short-Term Obligations and Long-Term Obligations were combined into Total Debt for training purposes. Other Liabilities were assumed to be
A43: $1,000 in all years.

Sheet Cash Flow Statement
A1: =+'Income Statement'!A1 -> Pepsico Financial Model | L1: This document subject to the Terms of Use
A2: Cash Flow Statement ($ in Millions) | L2: © 2013 Adventis CG Training LLC
E6: Fiscal Year Ended December 31,
E7: 2016A | F7: 2017A | G7: 2018A | H7: 2019E | I7: 2020E | J7: 2021E | K7: 2022E | L7: 2023E | N7: Instructions:
A8: Cash Flow Statement
A10: Net Earnings | H10: =+'Income Statement'!H25 -> 7275.6704 | I10: =+'Income Statement'!I25 -> 7404.7042 | J10: =+'Income Statement'!J25 -> 7606.9765 | K10: =+'Income Statement'!K25 -> 7800.0869 | L10: =+'Income Statement'!L25 -> 7950.5142 | N10: Step 8: Link into the Income Statement
A11: Depreciation | H11: =-'PP&E'!H12 -> 2481.6892 | I11: =-'PP&E'!I12 -> 2585.2017 | J11: =-'PP&E'!J12 -> 2704.5187 | K11: =-'PP&E'!K12 -> 2813.7137 | L11: =-'PP&E'!L12 -> 2911.1643 | N11: Step 6: Link into the PP&E Schedule
A12: Change in Working Capital | H12: =-'Working Capital'!H19 -> -912.6307 | I12: =-'Working Capital'!I19 -> 114.2935 | J12: =-'Working Capital'!J19 -> 107.96834 | K12: =-'Working Capital'!K19 -> 97.779467 | L12: =-'Working Capital'!L19 -> 66.164106 | N12: Step 7: Link into the Working Capital Schedule
A13: Cash From Operating Activities | H13: =SUM(H10:H12) -> 8844.7289 | I13: =SUM(I10:I12) -> 10104.199 | J13: =SUM(J10:J12) -> 10419.464 | K13: =SUM(K10:K12) -> 10711.58 | L13: =SUM(L10:L12) -> 10927.843
A15: Capital Expenditures | H15: =-'PP&E'!H11 -> -3004.1501 | I15: =-'PP&E'!I11 -> -2982.9251 | J15: =-'PP&E'!J11 -> -2974.9706 | K15: =-'PP&E'!K11 -> -2950.968 | L15: =-'PP&E'!L11 -> -2911.1643 | N15: Step 6: Link into the PP&E Schedule
A16: Cash From Investing Activities | H16: =SUM(H15:H15) -> -3004.1501 | I16: =SUM(I15:I15) -> -2982.9251 | J16: =SUM(J15:J15) -> -2974.9706 | K16: =SUM(K15:K15) -> -2950.968 | L16: =SUM(L15:L15) -> -2911.1643
A18: Dividends | H18: =-Equity!H41 -> -5053.6164 | I18: =-Equity!I41 -> -5232.7919 | J18: =-Equity!J41 -> -5418.187 | K18: =-Equity!K41 -> -5540.9915 | L18: =-Equity!L41 -> -5671.1874 | N18: Step 8: Link into the Equity Schedule
A19: Share Repurchases | H19: =-Equity!H32 -> -2000 | I19: =-Equity!I32 -> -1500 | J19: =-Equity!J32 -> -1500 | K19: =-Equity!K32 -> -1000 | L19: =-Equity!L32 -> -1000 | N19: Step 8: Link into the Equity Schedule
A20: Change in Revolver | H20: =Debt!H40 -> 0 | I20: =Debt!I40 -> 0 | J20: =Debt!J40 -> 808.24915 | K20: =Debt!K40 -> -219.62052 | L20: =Debt!L40 -> -345.49091 | N20: Step 9: Link into the Debt Schedule
A21: Change in Long-Term Debt | H21: =+Debt!H41 -> -1000 | I21: =+Debt!I41 -> -1000 | J21: =+Debt!J41 -> -8000 | K21: =+Debt!K41 -> -1000 | L21: =+Debt!L41 -> -1000 | N21: Step 9: Link into the Debt Schedule
A22: Cash From Financing Activities | H22: =SUM(H18:H21) -> -8053.6164 | I22: =SUM(I18:I21) -> -7732.7919 | J22: =SUM(J18:J21) -> -14109.938 | K22: =SUM(K18:K21) -> -7760.612 | L22: =SUM(L18:L21) -> -8016.6783
A24: Change in Cash | H24: =SUM(H22,H16,H13) -> -2213.0375 | I24: =SUM(I22,I16,I13) -> -611.51754 | J24: =SUM(J22,J16,J13) -> -6665.4449 | K24: =SUM(K22,K16,K13) -> 0 | L24: =SUM(L22,L16,L13) -> 0
A26: Beginning Cash | H26: =+G27 -> 10990 | I26: =+H27 -> 8776.9625 | J26: =+I27 -> 8165.4449 | K26: =+J27 -> 1500 | L26: =+K27 -> 1500 | N26: Step 5: Link to the ending balance of the previous year
A27: Ending Cash | G27: =+'Balance Sheet'!G10 -> 10990 | H27: =SUM(H26,H24) -> 8776.9625 | I27: =SUM(I26,I24) -> 8165.4449 | J27: =SUM(J26,J24) -> 1500 | K27: =SUM(K26,K24) -> 1500 | L27: =SUM(L26,L24) -> 1500 | N27: Step 5: Link 2018A into the Balance Sheet
A29: Metrics & Drivers
A30: Free Cash Flow (Levered) | H30: =SUM(H13,H16) -> 5840.5788 | I30: =SUM(I13,I16) -> 7121.2743 | J30: =SUM(J13,J16) -> 7444.4929 | K30: =SUM(K13,K16) -> 7760.612 | L30: =SUM(L13,L16) -> 8016.6783 | N30: Cash Flow from Operating Activities - Capital Expenditures
A31: Operating Income | H31: =+'Income Statement'!H14 -> 10449.218 | I31: =+'Income Statement'!I14 -> 10605.956 | J31: =+'Income Statement'!J14 -> 10818.075 | K31: =+'Income Statement'!K14 -> 10980.346 | L31: =+'Income Statement'!L14 -> 11090.15 | N31: Link to the Income Statement
A32: EBITDA | H32: =+H31+H11 -> 12930.907 | I32: =+I31+I11 -> 13191.158 | J32: =+J31+J11 -> 13522.594 | K32: =+K31+K11 -> 13794.06 | L32: =+L31+L11 -> 14001.314 | N32: Operating Income + Depreciation

Sheet PP&E
A1: =+'Income Statement'!A1 -> Pepsico Financial Model | L1: This document subject to the Terms of Use
A2: PP&E Schedule ($ in Millions) | L2: © 2013 Adventis CG Training LLC
E6: Fiscal Year Ended December 31,
E7: 2016A | F7: 2017A | G7: 2018A | H7: 2019E | I7: 2020E | J7: 2021E | K7: 2022E | L7: 2023E | N7: Instructions:
A8: PP&E Schedule
A10: Beginning Balance of PP&E | H10: =+G13 -> 17589 | I10: =+H13 -> 18111.461 | J10: =+I13 -> 18509.184 | K10: =+J13 -> 18779.636 | L10: =+K13 -> 18916.89 | N10: Link to the ending balance of the previous year
A11: Plus: Capital Expenditures | E11: 3040 | F11: 2969 | G11: 3282 | H11: =+H16*H17 -> 3004.1501 | I11: =+I16*I17 -> 2982.9251 | J11: =+J16*J17 -> 2974.9706 | K11: =+K16*K17 -> 2950.968 | L11: =+L16*L17 -> 2911.1643 | N11: Revenue x Capital Expenditures as a % Revenue
A12: Less: Depreciation | E12: -2368 | F12: -2369 | G12: -2399 | H12: =-H16*H18 -> -2481.6892 | I12: =-I16*I18 -> -2585.2017 | J12: =-J16*J18 -> -2704.5187 | K12: =-K16*K18 -> -2813.7137 | L12: =-L16*L18 -> -2911.1643 | N12: Revenue x Depreciation as a % Revenue
A13: Ending Balance of PP&E | G13: =+'Balance Sheet'!G15 -> 17589 | H13: =SUM(H10:H12) -> 18111.461 | I13: =SUM(I10:I12) -> 18509.184 | J13: =SUM(J10:J12) -> 18779.636 | K13: =SUM(K10:K12) -> 18916.89 | L13: =SUM(L10:L12) -> 18916.89 | N13: Link 2018A into the Balance Sheet
A15: Metrics & Drivers
A16: Revenue | E16: =+'Income Statement'!E10 -> 62799 | F16: =+'Income Statement'!F10 -> 63525 | G16: =+'Income Statement'!G10 -> 64661 | H16: =+'Income Statement'!H10 -> 65307.61 | I16: =+'Income Statement'!I10 -> 66287.224 | J16: =+'Income Statement'!J10 -> 67612.969 | K16: =+'Income Statement'!K10 -> 68627.163 | L16: =+'Income Statement'!L10 -> 69313.435 | N16: Link into the Income Statement
A17: Capital Expenditures as a % Revenue | E17: =+E11/E16 -> 0.048408414 | F17: =+F11/F16 -> 0.046737505 | G17: =+G11/G16 -> 0.050757025 | H17: 0.046 | I17: 0.045 | J17: 0.044 | K17: 0.043 | L17: 0.042 | N17: Capital Expenditures / Revenue
A18: Depreciation as a % Revenue | E18: =-E12/E16 -> 0.037707607 | F18: =-F12/F16 -> 0.037292405 | G18: =-G12/G16 -> 0.037101189 | H18: 0.038 | I18: 0.039 | J18: 0.04 | K18: 0.041 | L18: 0.042 | N18: Depreciation / Revenue

Sheet Working Capital
A1: =+'Income Statement'!A1 -> Pepsico Financial Model | L1: This document subject to the Terms of Use
A2: Working Capital Schedule ($ in Millions) | L2: © 2013 Adventis CG Training LLC
E6: Fiscal Year Ended December 31,
E7: 2016A | F7: 2017A | G7: 2018A | H7: 2019E | I7: 2020E | J7: 2021E | K7: 2022E | L7: 2023E | N7: Instructions:
A8: Working Capital Schedule
A10: Accounts Receivable | E10: =+'Balance Sheet'!E11 -> 6694 | F10: =+'Balance Sheet'!F11 -> 7024 | G10: =+'Balance Sheet'!G11 -> 7142 | H10: =H23/H27*H22 -> 7156.9984 | I10: =I23/I27*I22 -> 7244.5054 | J10: =J23/J27*J22 -> 7409.6404 | K10: =K23/K27*K22 -> 7520.785 | L10: =L23/L27*L22 -> 7595.9929 | N10: Days Receivable x Revenue / Days
A11: Other Current Assets | E11: =+'Balance Sheet'!E12 -> 3631 | F11: =+'Balance Sheet'!F12 -> 4493 | G11: =+'Balance Sheet'!G12 -> 3761 | H11: =+H24*H22 -> 3918.4566 | I11: =+I24*I22 -> 3977.2334 | J11: =+J24*J22 -> 4056.7781 | K11: =+K24*K22 -> 4117.6298 | L11: =+L24*L22 -> 4158.8061 | N11: Revenue x Other Current Assets as a % of Revenue
A12: Non-Cash Current Assets | E12: =SUM(E10:E11) -> 10325 | F12: =SUM(F10:F11) -> 11517 | G12: =SUM(G10:G11) -> 10903 | H12: =SUM(H10:H11) -> 11075.455 | I12: =SUM(I10:I11) -> 11221.739 | J12: =SUM(J10:J11) -> 11466.419 | K12: =SUM(K10:K11) -> 11638.415 | L12: =SUM(L10:L11) -> 11754.799
A14: Accounts Payable | E14: =+'Balance Sheet'!E19 -> 13243 | F14: =+'Balance Sheet'!F19 -> 14017 | G14: =+'Balance Sheet'!G19 -> 17112 | H14: =+H25*H$22 -> 16326.903 | I14: =+I25*I$22 -> 16571.806 | J14: =+J25*J$22 -> 16903.242 | K14: =+K25*K$22 -> 17156.791 | L14: =+L25*L$22 -> 17328.359 | N14: Revenue x Accounts Payable as a % of Revenue
A15: Other Current Liabilities | E15: =+'Balance Sheet'!E20 -> 1000 | F15: =+'Balance Sheet'!F20 -> 1000 | G15: =+'Balance Sheet'!G20 -> 1000 | H15: =+H26*H$22 -> 1044.9218 | I15: =+I26*I$22 -> 1060.5956 | J15: =+J26*J$22 -> 1081.8075 | K15: =+K26*K$22 -> 1098.0346 | L15: =+L26*L$22 -> 1109.015 | N15: Revenue x Other Current Liabilities as a % of Revenue
A16: Non-Debt Current Liabilities | E16: =SUM(E14:E15) -> 14243 | F16: =SUM(F14:F15) -> 15017 | G16: =SUM(G14:G15) -> 18112 | H16: =SUM(H14:H15) -> 17371.824 | I16: =SUM(I14:I15) -> 17632.402 | J16: =SUM(J14:J15) -> 17985.05 | K16: =SUM(K14:K15) -> 18254.825 | L16: =SUM(L14:L15) -> 18437.374
A18: Working Capital | E18: =E12-E16 -> -3918 | F18: =F12-F16 -> -3500 | G18: =G12-G16 -> -7209 | H18: =+H12-H16 -> -6296.3693 | I18: =+I12-I16 -> -6410.6628 | J18: =+J12-J16 -> -6518.6311 | K18: =+K12-K16 -> -6616.4106 | L18: =+L12-L16 -> -6682.5747 | N18: Non-Cash Current Assets - Non-Debt Current Liabilities
A19: Change in Working Capital | F19: =+F18-E18 -> 418 | G19: =+G18-F18 -> -3709 | H19: =+H18-G18 -> 912.6307 | I19: =+I18-H18 -> -114.2935 | J19: =+J18-I18 -> -107.96834 | K19: =+K18-J18 -> -97.779467 | L19: =+L18-K18 -> -66.164106 | N19: Current Year's Working Capital - Last Year's Working Capital
A21: Metrics & Drivers
A22: Revenue | E22: =+'Income Statement'!E10 -> 62799 | F22: =+'Income Statement'!F10 -> 63525 | G22: =+'Income Statement'!G10 -> 64661 | H22: =+'Income Statement'!H10 -> 65307.61 | I22: =+'Income Statement'!I10 -> 66287.224 | J22: =+'Income Statement'!J10 -> 67612.969 | K22: =+'Income Statement'!K10 -> 68627.163 | L22: =+'Income Statement'!L10 -> 69313.435 | N22: Link into the Income Statement
A23: Days Receivable | E23: =E10/E22*E27 -> 39.013424 | F23: =F10/F22*F27 -> 40.358284 | G23: =G10/G22*G27 -> 40.315337 | H23: 40 | I23: 40 | J23: 40 | K23: 40 | L23: 40 | N23: Accounts Receivable / Revenue x Days
A24: Other Current Assets as a % Revenue | E24: =E11/E$22 -> 0.057819392 | F24: =F11/F$22 -> 0.07072806 | G24: =G11/G$22 -> 0.058164891 | H24: 0.06 | I24: 0.06 | J24: 0.06 | K24: 0.06 | L24: 0.06 | N24: Other Current Assets / Revenue
A25: Accounts Payable as a % Revenue | E25: =E14/E$22 -> 0.21087915 | F25: =F14/F$22 -> 0.22065329 | G25: =G14/G$22 -> 0.26464175 | H25: 0.25 | I25: 0.25 | J25: 0.25 | K25: 0.25 | L25: 0.25 | N25: Accounts Payable / Revenue
A26: Other Current Liabilities as a % Revenue | E26: =E15/E$22 -> 0.01592382 | F26: =F15/F$22 -> 0.015741834 | G26: =G15/G$22 -> 0.015465273 | H26: 0.016 | I26: 0.016 | J26: 0.016 | K26: 0.016 | L26: 0.016 | N26: Other Current Liabilities / Revenue
A27: Days | E27: 366 | F27: 365 | G27: 365 | H27: 365 | I27: 366 | J27: 365 | K27: 365 | L27: 365

Sheet Equity
A1: =+'Income Statement'!A1 -> Pepsico Financial Model | L1: This document subject to the Terms of Use
A2: Equity Schedule ($ in Millions) | L2: © 2013 Adventis CG Training LLC
E6: Fiscal Year Ended December 31,
E7: 2016A | F7: 2017A | G7: 2018A | H7: 2019E | I7: 2020E | J7: 2021E | K7: 2022E | L7: 2023E | N7: Instructions:
A8: Equity Schedule
A10: Beginning Balance of Equity | H10: =+G14 -> 14602 | I10: =+H14 -> 14824.054 | J10: =+I14 -> 15495.966 | K10: =+J14 -> 16184.756 | L10: =+K14 -> 17443.851 | N10: Link to the ending balance of the previous year
A11: Plus: Net Earnings | H11: =+'Income Statement'!H25 -> 7275.6704 | I11: =+'Income Statement'!I25 -> 7404.7042 | J11: =+'Income Statement'!J25 -> 7606.9765 | K11: =+'Income Statement'!K25 -> 7800.0869 | L11: =+'Income Statement'!L25 -> 7950.5142 | N11: Link into the Income Statement
A12: Less: Dividends | H12: =-H41 -> -5053.6164 | I12: =-I41 -> -5232.7919 | J12: =-J41 -> -5418.187 | K12: =-K41 -> -5540.9915 | L12: =-L41 -> -5671.1874 | N12: Link into the Dividend Schedule
A13: Less: Share Repurchases | H13: =-H32 -> -2000 | I13: =-I32 -> -1500 | J13: =-J32 -> -1500 | K13: =-K32 -> -1000 | L13: =-L32 -> -1000 | N13: Link into the Share Repurchase Schedule
A14: Ending Balance of Equity | G14: =+'Balance Sheet'!G27 -> 14602 | H14: =SUM(H10:H13) -> 14824.054 | I14: =SUM(I10:I13) -> 15495.966 | J14: =SUM(J10:J13) -> 16184.756 | K14: =SUM(K10:K13) -> 17443.851 | L14: =SUM(L10:L13) -> 18723.178 | N14: Link 2018A into the Balance Sheet
A16: Common Stock Schedule
A18: Beginning Balance of Shares Outstanding | E18: 1448 | F18: =+E21 -> 1428 | G18: =+F21 -> 1420 | H18: =+G21 -> 1409 | I18: =+H21 -> 1398.5646 | J18: =+I21 -> 1392.2577 | K18: =+J21 -> 1386.2998 | L18: =+K21 -> 1384.196
A19: No. of Shares Repurchased | E19: -29 | F19: -18 | G19: -18 | H19: =-H30 -> -15.435359 | I19: =-I30 -> -11.306957 | J19: =-J30 -> -10.957931 | K19: =-K30 -> -7.1037561 | L19: =-L30 -> -6.9591294 | N19: Link to row 30
A20: No. of Shares Issued | E20: 9 | F20: 10 | G20: 7 | H20: 5 | I20: 5 | J20: 5 | K20: 5 | L20: 5
A21: Ending Balance of Shares Outstanding | E21: =SUM(E18:E20) -> 1428 | F21: =SUM(F18:F20) -> 1420 | G21: =SUM(G18:G20) -> 1409 | H21: =SUM(H18:H20) -> 1398.5646 | I21: =SUM(I18:I20) -> 1392.2577 | J21: =SUM(J18:J20) -> 1386.2998 | K21: =SUM(K18:K20) -> 1384.196 | L21: =SUM(L18:L20) -> 1382.2369
A23: Metrics & Drivers
A24: Average Common Shares Outstanding | E24: 1439 | F24: 1425 | G24: 1415 | H24: =AVERAGE(H21,H18) -> 1403.7823 | I24: =AVERAGE(I21,I18) -> 1395.4112 | J24: =AVERAGE(J21,J18) -> 1389.2787 | K24: =AVERAGE(K21,K18) -> 1385.2479 | L24: =AVERAGE(L21,L18) -> 1383.2164 | N24: =Average (Beginning Balance of Shares Outstanding, Ending Balance of Shares Outstanding)
A25: Net Earnings | E25: =+'Income Statement'!E25 -> 6379 | F25: =+'Income Statement'!F25 -> 4908 | G25: =+'Income Statement'!G25 -> 12559 | H25: =+'Income Statement'!H25 -> 7275.6704 | I25: =+'Income Statement'!I25 -> 7404.7042 | J25: =+'Income Statement'!J25 -> 7606.9765 | K25: =+'Income Statement'!K25 -> 7800.0869 | L25: =+'Income Statement'!L25 -> 7950.5142 | N25: Link into the Income Statement
A26: Basic Earnings per Share | E26: =+E25/E24 -> 4.4329395 | F26: =+F25/F24 -> 3.4442105 | G26: =+G25/G24 -> 8.8756184 | H26: =+H25/H24 -> 5.182905 | I26: =+I25/I24 -> 5.3064676 | J26: =+J25/J24 -> 5.4754862 | K26: =+K25/K24 -> 5.6308239 | L26: =+L25/L24 -> 5.7478454 | N26: Net Earnings / Average Common Shares Outstanding
A28: Share Repurchases Schedule
A30: No. of Shares Repurchased | E30: =-E19 -> 29 | F30: =-F19 -> 18 | G30: =-G19 -> 18 | H30: =+H32/H31 -> 15.435359 | I30: =+I32/I31 -> 11.306957 | J30: =+J32/J31 -> 10.957931 | K30: =+K32/K31 -> 7.1037561 | L30: =+L32/L31 -> 6.9591294 | N30: Link to row 19; Share Repurchases ($) / Average Price Paid per Share
A31: x Average Price Paid per Share | E31: =+E32/E30 -> 103.44828 | F31: =+F32/F30 -> 111.11111 | G31: =+G32/G30 -> 111.11111 | H31: =+H26*H35 -> 129.57263 | I31: =+I26*I35 -> 132.66169 | J31: =+J26*J35 -> 136.88716 | K31: =+K26*K35 -> 140.7706 | L31: =+L26*L35 -> 143.69613 | N31: Share Repurchases ($) / No. of Shares Repurchased; P/E Multiple * Basic Earnings per Share
A32: Share Repurchases ($) | E32: 3000 | F32: 2000 | G32: 2000 | H32: 2000 | I32: 1500 | J32: 1500 | K32: 1000 | L32: 1000
A34: Metrics & Drivers
A35: P/E Multiple | E35: =+E31/E26 -> 23.33627 | F35: =+F31/F26 -> 32.260255 | G35: =+G31/G26 -> 12.51869 | H35: 25 | I35: 25 | J35: 25 | K35: 25 | L35: 25 | N35: Average Price Paid per Share / Basic Earnings per Share
A37: Dividends Schedule
A39: Average Common Shares Outstanding | E39: =+E24 -> 1439 | F39: =+F24 -> 1425 | G39: =+G24 -> 1415 | H39: =+H24 -> 1403.7823 | I39: =+I24 -> 1395.4112 | J39: =+J24 -> 1389.2787 | K39: =+K24 -> 1385.2479 | L39: =+L24 -> 1383.2164 | N39: Link to row 24
A40: x Dividends per Share | E40: =+E41/E39 -> 2.9374566 | F40: =+F41/F39 -> 1 | G40: =+G41/G39 -> 3.4840989 | H40: 3.6 | I40: 3.75 | J40: 3.9 | K40: 4 | L40: 4.1 | N40: Dividends ($) / Average Common Shares Outstanding
A41: Dividends ($) | E41: 4227 | F41: 1425 | G41: 4930 | H41: =+H39*H40 -> 5053.6164 | I41: =+I39*I40 -> 5232.7919 | J41: =+J39*J40 -> 5418.187 | K41: =+K39*K40 -> 5540.9915 | L41: =+L39*L40 -> 5671.1874 | N41: Average Common Shares Outstanding x Dividends per Share
A43: Metrics & Drivers
A44: Dividend Yield | E44: =+E40/E31 -> 0.028395413 | F44: =+F40/F31 -> 0.009 | G44: =+G40/G31 -> 0.03135689 | H44: =+H40/H31 -> 0.027783646 | I44: =+I40/I31 -> 0.028267392 | J44: =+J40/J31 -> 0.028490621 | K44: =+K40/K31 -> 0.028415025 | L44: =+L40/L31 -> 0.028532431 | N44: Dividend per Share / Average Price Paid per Share

Sheet Debt
A1: =+'Income Statement'!A1 -> Pepsico Financial Model | L1: This document subject to the Terms of Use
A2: Debt Schedule ($ in Millions) | L2: © 2013 Adventis CG Training LLC
E6: Fiscal Year Ended December 31,
E7: 2016A | F7: 2017A | G7: 2018A | H7: 2019E | I7: 2020E | J7: 2021E | K7: 2022E | L7: 2023E | N7: Instructions:
A8: Beginning Debt
A10: Revolver Beginning Balance | H10: =+G35 -> 0 | I10: =+H35 -> 0 | J10: =+I35 -> 0 | K10: =+J35 -> 808.24915 | L10: =+K35 -> 588.62863 | N10: Link to the Ending Balance of the previous year
A11: Long-Term Debt Beginning Balance | H11: =+G36 -> 32321 | I11: =+H36 -> 31321 | J11: =+I36 -> 30321 | K11: =+J36 -> 22321 | L11: =+K36 -> 21321 | N11: Link to the Ending Balance of the previous year
A12: Total Beginning Debt Balance | H12: =SUM(H10:H11) -> 32321 | I12: =SUM(I10:I11) -> 31321 | J12: =SUM(J10:J11) -> 30321 | K12: =SUM(K10:K11) -> 23129.249 | L12: =SUM(L10:L11) -> 21909.629
A14: Debt Pay Down and Issuance
A16: Beginning Cash Balance | H16: =+'Balance Sheet'!G10 -> 10990 | I16: =+'Balance Sheet'!H10 -> 8776.9625 | J16: =+'Balance Sheet'!I10 -> 8165.4449 | K16: =+'Balance Sheet'!J10 -> 1500 | L16: =+'Balance Sheet'!K10 -> 1500 | N16: Link into the Balance Sheet
A17: Cash From Operating Activities | H17: =+'Cash Flow Statement'!H13 -> 8844.7289 | I17: =+'Cash Flow Statement'!I13 -> 10104.199 | J17: =+'Cash Flow Statement'!J13 -> 10419.464 | K17: =+'Cash Flow Statement'!K13 -> 10711.58 | L17: =+'Cash Flow Statement'!L13 -> 10927.843 | N17: Link into the Cash Flow Statement
A18: Cash From Investing Activities | H18: =+'Cash Flow Statement'!H16 -> -3004.1501 | I18: =+'Cash Flow Statement'!I16 -> -2982.9251 | J18: =+'Cash Flow Statement'!J16 -> -2974.9706 | K18: =+'Cash Flow Statement'!K16 -> -2950.968 | L18: =+'Cash Flow Statement'!L16 -> -2911.1643 | N18: Link into the Cash Flow Statement
A19: Dividends | H19: =-Equity!H41 -> -5053.6164 | I19: =-Equity!I41 -> -5232.7919 | J19: =-Equity!J41 -> -5418.187 | K19: =-Equity!K41 -> -5540.9915 | L19: =-Equity!L41 -> -5671.1874 | N19: Link into the Cash Flow Statement
A20: Share Repurchases | H20: =-Equity!H32 -> -2000 | I20: =-Equity!I32 -> -1500 | J20: =-Equity!J32 -> -1500 | K20: =-Equity!K32 -> -1000 | L20: =-Equity!L32 -> -1000 | N20: Link into the Cash Flow Statement
A21: Long-Term Debt Paydown (Scheduled) | H21: -1000 | I21: -1000 | J21: -8000 | K21: -1000 | L21: -1000
A22: Less: Minimum Cash Balance | H22: -1500 | I22: -1500 | J22: -1500 | K22: -1500 | L22: -1500
A23: Total Cash Available (Required) | H23: =SUM(H16:H22) -> 7276.9625 | I23: =SUM(I16:I22) -> 6665.4449 | J23: =SUM(J16:J22) -> -808.24915 | K23: =SUM(K16:K22) -> 219.62052 | L23: =SUM(L16:L22) -> 345.49091
A25: Revolver Issued | H25: =IF(H23<0,-H23,0) -> 0 | I25: =IF(I23<0,-I23,0) -> 0 | J25: =IF(J23<0,-J23,0) -> 808.24915 | K25: =IF(K23<0,-K23,0) -> 0 | L25: =IF(L23<0,-L23,0) -> 0 | N25: =IF(H23<0,-H23,0)
A26: Long-Term Debt Issued | H26: 0 | I26: 0 | J26: 0 | K26: 0 | L26: 0
A27: Total Cash Available | H27: =SUM(H25:H26,H23) -> 7276.9625 | I27: =SUM(I25:I26,I23) -> 6665.4449 | J27: =SUM(J25:J26,J23) -> 0 | K27: =SUM(K25:K26,K23) -> 219.62052 | L27: =SUM(L25:L26,L23) -> 345.49091
A29: Revolver Paydown | H29: =-IF(H27>0,MIN(H10,H27),0) -> 0 | I29: =-IF(I27>0,MIN(I10,I27),0) -> 0 | J29: =-IF(J27>0,MIN(J10,J27),0) -> 0 | K29: =-IF(K27>0,MIN(K10,K27),0) -> -219.62052 | L29: =-IF(L27>0,MIN(L10,L27),0) -> -345.49091 | N29: =-IF(H27>0,MIN(H10,H27),0)
A30: Long-Term Debt Paydown | H30: =+H21 -> -1000 | I30: =+I21 -> -1000 | J30: =+J21 -> -8000 | K30: =+K21 -> -1000 | L30: =+L21 -> -1000 | N30: Link into row 21
A31: Total Debt Paydown | H31: =SUM(H29:H30) -> -1000 | I31: =SUM(I29:I30) -> -1000 | J31: =SUM(J29:J30) -> -8000 | K31: =SUM(K29:K30) -> -1219.6205 | L31: =SUM(L29:L30) -> -1345.4909
A33: Ending Debt
A35: Revolver Ending Balance | G35: 0 | H35: =SUM(H10,H29,H25) -> 0 | I35: =SUM(I10,I29,I25) -> 0 | J35: =SUM(J10,J29,J25) -> 808.24915 | K35: =SUM(K10,K29,K25) -> 588.62863 | L35: =SUM(L10,L29,L25) -> 243.13772 | N35: Beginning Revolver Balance + Revolver Issued + Revolver Paydown
A36: Long-Term Debt Ending Balance | G36: 32321 | H36: =SUM(H11,H30,H26) -> 31321 | I36: =SUM(I11,I30,I26) -> 30321 | J36: =SUM(J11,J30,J26) -> 22321 | K36: =SUM(K11,K30,K26) -> 21321 | L36: =SUM(L11,L30,L26) -> 20321 | N36: Beginning Long-Term Debt Balance + Long-Term Debt Issued + Long-Term Debt Paydown
A37: Total Ending Debt Balance | G37: =SUM(G35:G36) -> 32321 | H37: =SUM(H35:H36) -> 31321 | I37: =SUM(I35:I36) -> 30321 | J37: =SUM(J35:J36) -> 23129.249 | K37: =SUM(K35:K36) -> 21909.629 | L37: =SUM(L35:L36) -> 20564.138
A39: Metrics & Drivers
A40: Change in Revolver | H40: =SUM(H25,H29) -> 0 | I40: =SUM(I25,I29) -> 0 | J40: =SUM(J25,J29) -> 808.24915 | K40: =SUM(K25,K29) -> -219.62052 | L40: =SUM(L25,L29) -> -345.49091 | N40: Revolver Issued + Revolver Paydown
A41: Change in Long-Term Debt | H41: =SUM(H26,H30) -> -1000 | I41: =SUM(I26,I30) -> -1000 | J41: =SUM(J26,J30) -> -8000 | K41: =SUM(K26,K30) -> -1000 | L41: =SUM(L26,L30) -> -1000 | N41: Long-Term Debt Issued + Long-Term Debt Paydown
A42: EBITDA | H42: =+'Cash Flow Statement'!H32 -> 12930.907 | I42: =+'Cash Flow Statement'!I32 -> 13191.158 | J42: =+'Cash Flow Statement'!J32 -> 13522.594 | K42: =+'Cash Flow Statement'!K32 -> 13794.06 | L42: =+'Cash Flow Statement'!L32 -> 14001.314 | N42: Link to the Cash Flow Statement
A43: Shareholders' Equity | H43: =+'Balance Sheet'!H27 -> 14824.054 | I43: =+'Balance Sheet'!I27 -> 15495.966 | J43: =+'Balance Sheet'!J27 -> 16184.756 | K43: =+'Balance Sheet'!K27 -> 17443.851 | L43: =+'Balance Sheet'!L27 -> 18723.178 | N43: Link to the Balance Sheet
A44: Debt / EBITDA | H44: =+H37/H42 -> 2.4221813 | I44: =+I37/I42 -> 2.2985852 | J44: =+J37/J42 -> 1.7104151 | K44: =+K37/K42 -> 1.5883379 | L44: =+L37/L42 -> 1.4687291 | N44: Total Ending Debt Balance / EBITDA
A45: Debt-to-Equity Ratio | H45: =+H37/H43 -> 2.1128498 | I45: =+I37/I43 -> 1.9567028 | J45: =+J37/J43 -> 1.4290762 | K45: =+K37/K43 -> 1.2560087 | L45: =+L37/L43 -> 1.0983252 | N45: Total Ending Debt Balance / Shareholders' Equity

Sheet Interest
A1: =+'Income Statement'!A1 -> Pepsico Financial Model | L1: This document subject to the Terms of Use
A2: Interest Schedule ($ in Millions) | L2: © 2013 Adventis CG Training LLC
E6: Fiscal Year Ended December 31,
E7: 2016A | F7: 2017A | G7: 2018A | H7: 2019E | I7: 2020E | J7: 2021E | K7: 2022E | L7: 2023E | N7: Instructions:
A8: Interest Expense Schedule
A10: Revolver Average Balance | H10: =AVERAGE(H23,H25) -> 0 | I10: =AVERAGE(I23,I25) -> 0 | J10: =AVERAGE(J23,J25) -> 404.12457 | K10: =AVERAGE(K23,K25) -> 698.43889 | L10: =AVERAGE(L23,L25) -> 415.88318 | N10: =Average(Revolver Beginning Balance,Revolver Ending Balance)
A11: Long-Term Debt Average Balance | H11: =AVERAGE(H24,H26) -> 31821 | I11: =AVERAGE(I24,I26) -> 30821 | J11: =AVERAGE(J24,J26) -> 26321 | K11: =AVERAGE(K24,K26) -> 21821 | L11: =AVERAGE(L24,L26) -> 20821 | N11: =Average(Long-Term Debt Beginning Balance,Long-Term Debt Ending Balance)
A12: Average Debt Balance | H12: =SUM(H10:H11) -> 31821 | I12: =SUM(I10:I11) -> 30821 | J12: =SUM(J10:J11) -> 26725.125 | K12: =SUM(K10:K11) -> 22519.439 | L12: =SUM(L10:L11) -> 21236.883
A14: Revolver Interest Rate | H14: 0.03 | I14: 0.03 | J14: 0.03 | K14: 0.03 | L14: 0.03
A15: Long-Term Debt Interest Rate | H15: 0.035 | I15: 0.035 | J15: 0.035 | K15: 0.035 | L15: 0.035
A16: Average Interest Rate | H16: =H20/H12 -> 0.035 | I16: =I20/I12 -> 0.035 | J16: =J20/J12 -> 0.034924392 | K16: =K20/K12 -> 0.034844925 | L16: =L20/L12 -> 0.034902085 | N16: Total Interest Expense / Average Debt Balance
A18: Revolver Interest Expense | H18: =+H10*H14 -> 0 | I18: =+I10*I14 -> 0 | J18: =+J10*J14 -> 12.123737 | K18: =+K10*K14 -> 20.953167 | L18: =+L10*L14 -> 12.476495 | N18: Revolver Average Balance x Revolver Interest Rate
A19: Long-Term Debt Interest Expense | H19: =+H11*H15 -> 1113.735 | I19: =+I11*I15 -> 1078.735 | J19: =+J11*J15 -> 921.235 | K19: =+K11*K15 -> 763.735 | L19: =+L11*L15 -> 728.735 | N19: Long-Term Debt Average Balance x Long-Term Debt Interest Rate
A20: Total Interest Expense | H20: =SUM(H18:H19) -> 1113.735 | I20: =SUM(I18:I19) -> 1078.735 | J20: =SUM(J18:J19) -> 933.35874 | K20: =SUM(K18:K19) -> 784.68817 | L20: =SUM(L18:L19) -> 741.2115
A22: Metrics & Drivers
A23: Revolver Beginning Balance | H23: =Debt!H10 -> 0 | I23: =Debt!I10 -> 0 | J23: =Debt!J10 -> 0 | K23: =Debt!K10 -> 808.24915 | L23: =Debt!L10 -> 588.62863 | N23: Link into the Debt Schedule
A24: Long-Term Debt Beginning Balance | H24: =Debt!H11 -> 32321 | I24: =Debt!I11 -> 31321 | J24: =Debt!J11 -> 30321 | K24: =Debt!K11 -> 22321 | L24: =Debt!L11 -> 21321 | N24: Link into the Debt Schedule
A25: Revolver Ending Balance | H25: =Debt!H35 -> 0 | I25: =Debt!I35 -> 0 | J25: =Debt!J35 -> 808.24915 | K25: =Debt!K35 -> 588.62863 | L25: =Debt!L35 -> 243.13772 | N25: Link into the Debt Schedule
A26: Long-Term Debt Ending Balance | H26: =Debt!H36 -> 31321 | I26: =Debt!I36 -> 30321 | J26: =Debt!J36 -> 22321 | K26: =Debt!K36 -> 21321 | L26: =Debt!L36 -> 20321 | N26: Link into the Debt Schedule
A28: Interest Income Schedule
A30: Average Cash Balance | H30: =AVERAGE(H35,H36) -> 9883.4812 | I30: =AVERAGE(I35,I36) -> 8471.2037 | J30: =AVERAGE(J35,J36) -> 4832.7225 | K30: =AVERAGE(K35,K36) -> 1500 | L30: =AVERAGE(L35,L36) -> 1500 | N30: =Average(Cash Beginning Balance,Cash Ending Balance)
A31: Interest Rate on Cash | H31: 0.03 | I31: 0.03 | J31: 0.03 | K31: 0.03 | L31: 0.03
A32: Total Interest Income | H32: =H31*H30 -> 296.50444 | I32: =I31*I30 -> 254.13611 | J32: =J31*J30 -> 144.98167 | K32: =K31*K30 -> 45 | L32: =L31*L30 -> 45
A34: Metrics & Drivers
A35: Cash Beginning Balance | H35: =+'Cash Flow Statement'!H26 -> 10990 | I35: =+'Cash Flow Statement'!I26 -> 8776.9625 | J35: =+'Cash Flow Statement'!J26 -> 8165.4449 | K35: =+'Cash Flow Statement'!K26 -> 1500 | L35: =+'Cash Flow Statement'!L26 -> 1500 | N35: Link into the Cash Flow Statement
A36: Cash Ending Balance | H36: =+'Cash Flow Statement'!H27 -> 8776.9625 | I36: =+'Cash Flow Statement'!I27 -> 8165.4449 | J36: =+'Cash Flow Statement'!J27 -> 1500 | K36: =+'Cash Flow Statement'!K27 -> 1500 | L36: =+'Cash Flow Statement'!L27 -> 1500 | N36: Link into the Cash Flow Statement
